pymarstek/__init__.py
pymarstek/command_builder.py
pymarstek/const.py
pymarstek/udp.py
py_marstek-0.1.0.dist-info/METADATA
py_marstek-0.1.0.dist-info/WHEEL
py_marstek-0.1.0.dist-info/RECORD
