Metadata-Version: 2.4
Name: py-marstek
Version: 0.1.0
Summary: Asynchronous UDP client for Marstek energy storage systems
Project-URL: Homepage, https://github.com/MarstekEnergy/py-marstek
Author-email: MarstekEnergy <hame.shenzhen@gmail.com>
License: Apache-2.0
Requires-Python: >=3.11
Provides-Extra: psutil
Requires-Dist: psutil; extra == 'psutil'
